README.rst
README.txt
setup.py
lnevx_alg/__init__.py
lnevx_alg/core.py
lnevx_alg.egg-info/PKG-INFO
lnevx_alg.egg-info/SOURCES.txt
lnevx_alg.egg-info/dependency_links.txt
lnevx_alg.egg-info/top_level.txt